Metadata-Version: 2.1
Name: pscp
Version: 0.0.3
Summary: Per-session checkpoint using git-stash-create
Home-page: https://github.com/qbx2/pscp
Author: Sunyeop Lee
Author-email: sunyeop97@gmail.com
License: MIT
Platform: UNKNOWN
Requires-Python: >=3.5
